CHANGELOG.md
README.md
mitol/__init__.py
mitol/google_sheets_deferrals/__init__.py
mitol/google_sheets_deferrals/admin.py
mitol/google_sheets_deferrals/api.py
mitol/google_sheets_deferrals/apps.py
mitol/google_sheets_deferrals/constants.py
mitol/google_sheets_deferrals/hooks.py
mitol/google_sheets_deferrals/models.py
mitol/google_sheets_deferrals/py.typed
mitol/google_sheets_deferrals/utils.py
mitol/google_sheets_deferrals/management/commands/process_deferral_requests.py
mitol/google_sheets_deferrals/migrations/0001_initial.py
mitol/google_sheets_deferrals/migrations/__init__.py
mitol/google_sheets_deferrals/settings/google_sheets_deferrals.py
mitol_django_google_sheets_deferrals-2025.3.17.dist-info/METADATA
mitol_django_google_sheets_deferrals-2025.3.17.dist-info/WHEEL
mitol_django_google_sheets_deferrals-2025.3.17.dist-info/RECORD
